autocoder_cli_sdk/__init__.py
autocoder_cli_sdk/async_client.py
autocoder_cli_sdk/client.py
autocoder_cli_sdk/diagnostics.py
autocoder_cli_sdk/models.py
autocoder_cli_sdk/process_manager.py
autocoder_cli_sdk/py.typed
autocoder_cli_sdk/pydantic_models.py
autocoder_cli_sdk-1.0.1.dist-info/METADATA
autocoder_cli_sdk-1.0.1.dist-info/WHEEL
autocoder_cli_sdk-1.0.1.dist-info/licenses/LICENSE
autocoder_cli_sdk-1.0.1.dist-info/RECORD
