Metadata-Version: 2.4
Name: autocoder-cli-sdk
Version: 1.0.1
Summary: Python SDK for AutoCoder CLI - 便于在Python代码中调用auto-coder.run功能
Project-URL: Homepage, https://github.com/your-org/auto-coder
Project-URL: Documentation, https://github.com/your-org/auto-coder/tree/master/cli-sdks/python
Project-URL: Repository, https://github.com/your-org/auto-coder
Project-URL: Bug Tracker, https://github.com/your-org/auto-coder/issues
Author-email: AutoCoder Team <support@autocoder.com>
License: MIT License
License-File: LICENSE
Keywords: ai,api,autocoder,cli,code-generation,python,sdk
Classifier: Development Status :: 4 - Beta
Classifier: Intended Audience :: Developers
Classifier: License :: OSI Approved :: MIT License
Classifier: Programming Language :: Python :: 3
Classifier: Programming Language :: Python :: 3.7
Classifier: Programming Language :: Python :: 3.8
Classifier: Programming Language :: Python :: 3.9
Classifier: Programming Language :: Python :: 3.10
Classifier: Programming Language :: Python :: 3.11
Classifier: Programming Language :: Python :: 3.12
Classifier: Topic :: Software Development :: Code Generators
Classifier: Topic :: Software Development :: Libraries :: Python Modules
Classifier: Topic :: Utilities
Requires-Python: >=3.7
Requires-Dist: psutil>=5.8.0
Requires-Dist: pydantic<3.0.0,>=1.8.0
Requires-Dist: typing-extensions>=3.7.4; python_version < '3.8'
Provides-Extra: dev
Requires-Dist: black>=21.0.0; extra == 'dev'
Requires-Dist: flake8>=3.8.0; extra == 'dev'
Requires-Dist: isort>=5.0.0; extra == 'dev'
Requires-Dist: mypy>=0.800; extra == 'dev'
Requires-Dist: pytest-asyncio>=0.18.0; extra == 'dev'
Requires-Dist: pytest-cov>=2.12.0; extra == 'dev'
Requires-Dist: pytest-mock>=3.6.0; extra == 'dev'
Requires-Dist: pytest>=6.0.0; extra == 'dev'
Provides-Extra: examples
Requires-Dist: rich>=10.0.0; extra == 'examples'
